{
  "doc_id": "native-websocket-guidelines",
  "title": "使用WebSocket访问网络(C/C++)",
  "path": "zh-cn/application-dev/network/native-websocket-guidelines.md",
  "relative_path": "../../docs/zh-cn/application-dev/network/native-websocket-guidelines.md",
  "metadata": {
    "kit": "Network Kit",
    "subsystem": "Communication",
    "owner": "@wmyao_mm",
    "designer": "@guo-min_net",
    "tester": "@tongxilin",
    "adviser": "@zhang_yixin13"
  },
  "summary": "介绍WebSocket模块的C/C++接口，提供建立服务器与客户端双向连接的能力。包括客户端构造、连接、发送、关闭等接口。使用Native C++开发。",
  "structure": {
    "title": "使用WebSocket访问网络(C/C++)",
    "sections": [
      {
        "section_id": "0001",
        "title": "场景介绍",
        "level": 2,
        "line_start": 9,
        "line_end": 13,
        "summary": "介绍WebSocket模块的功能，可以建立服务器与客户端的双向连接。"
      },
      {
        "section_id": "0002",
        "title": "接口说明",
        "level": 2,
        "line_start": 14,
        "line_end": 26,
        "summary": "列出WebSocket常用接口及其描述，包括客户端构造、连接、发送、关闭、销毁等。"
      },
      {
        "section_id": "0003",
        "title": "WebSocket接口开发示例",
        "level": 2,
        "line_start": 27,
        "line_end": 200,
        "summary": "详细介绍WebSocket接口的开发示例，包括创建Native C++工程、添加开发依赖、实现连接和通信功能等步骤。"
      }
    ]
  }
}