{
  "doc_id": "app-file-backup-overview",
  "title": "应用数据备份恢复概述",
  "path": "zh-cn/application-dev/file-management/app-file-backup-overview.md",
  "relative_path": "../../docs/zh-cn/application-dev/file-management/app-file-backup-overview.md",
  "metadata": {
    "kit": "Core File Kit",
    "subsystem": "FileManagement",
    "owner": "@lvzhenjie",
    "designer": "@wang_zhangjun; @chenxi0605",
    "tester": "@liuhonggang123",
    "adviser": "@jinqiuheng"
  },
  "summary": "介绍应用数据备份恢复的概念和作用，说明BackupExtensionAbility是Stage模型中扩展组件ExtensionAbility的派生类，用于提供备份及恢复应用数据的能力，分为应用接入数据备份恢复和应用触发数据备份恢复两种场景。",
  "structure": {
    "title": "应用数据备份恢复概述",
    "sections": []
  }
}