{
  "doc_id": "DeviceCertificateKit-Readme-CN",
  "title": "Device Certificate Kit（设备证书服务）",
  "path": "zh-cn/application-dev/security/DeviceCertificateKit/Readme-CN.md",
  "relative_path": "../../docs/zh-cn/application-dev/security/DeviceCertificateKit/Readme-CN.md",
  "metadata":. {
    "kit": "",
    "subsystem": "",
    "owner": "",
    "designer": "",
    "tester": "",
    "adviser": ""
  },
  "summary": "# Device Certificate Kit（设备证书服务） <!--Kit: Device Certificate Kit--> <!--Subsystem: Security--> <!--Owner: @zxz--3--; @chaceli--> <!--Designer: @lanming--; @chande--> <!--Tester: @PAFT-",
  "structure": {
    "title": "Device Certificate Kit（设备证书服务）",
    "sections": []
  }
}
