{
  "doc_id": "capi-ohaudio-oh-audiodevicedescriptor",
  "title": "OH_AudioDeviceDescriptor",
  "path": "zh-cn/application-dev/reference/apis-audio-kit/capi-ohaudio-oh-audiodevicedescriptor.md",
  "relative_path": "../../docs/zh-cn/application-dev/reference/apis-audio-kit/capi-ohaudio-oh-audiodevicedescriptor.md",
  "metadata": {
    "kit": "Audio Kit",
    "subsystem": "Multimedia",
    "owner": "@songshenke",
    "designer": "@caixuejiang; @hao-liangfei; @zhanganxiang",
    "tester": "@Filger",
    "adviser": "@w_Machine_cc"
  },
  "summary": "Audio Kit Multimedia 模块的 OH_AudioDeviceDescriptor，提供相关接口和功能说明。",
  "structure": {
    "title": "OH_AudioDeviceDescriptor",
    "sections": [
      {
        "section_id": "section-1",
        "title": "概述",
        "level": 2,
        "line_start": 13,
        "line_end": 23,
        "summary": "声明音频设备描述符。该实例用于获取更多音频设备详细信息属性。\n\n**起始版本：** 12\n\n**相关模块：** [OHAudio](capi-ohaudio.md)\n\n**所在头文件：** [nat"
      }
    ]
  }
}