{
  "doc_id": "capi-telephony-radio-type-h",
  "title": "telephony_radio_type.h",
  "path": "zh-cn/application-dev/reference/apis-telephony-kit/capi-telephony-radio-type-h.md",
  "relative_path": "../../docs/zh-cn/application-dev/reference/apis-telephony-kit/capi-telephony-radio-type-h.md",
  "metadata": {
    "kit": "Telephony Kit",
    "subsystem": "Telephony",
    "owner": "@Terence_Super",
    "designer": "@Terence_Super",
    "tester": "@jiang_99",
    "adviser": "@zhang_yixin13"
  },
  "summary": "Telephony Kit Telephony 模块的 telephony_radio_type.h，提供相关接口和功能说明。",
  "structure": {
    "title": "telephony_radio_type.h",
    "sections": [
      {
        "section_id": "section-1",
        "title": "概述",
        "level": 2,
        "line_start": 9,
        "line_end": 22,
        "summary": "定义网络搜索模块的C接口需要的数据结构。\n\n**引用文件：** <telephony/core_service/telephony_radio_type.h>\n\n**库：** libtelephon"
      },
      {
        "section_id": "section-2",
        "title": "汇总",
        "level": 2,
        "line_start": 23,
        "line_end": 46,
        "summary": "### 结构体\n\n| 名称 | typedef关键字 | 描述 |\n| -- | -- | -- |\n| [Telephony_NetworkState](capi-telephony-teleph"
      },
      {
        "section_id": "section-3",
        "title": "枚举类型说明",
        "level": 2,
        "line_start": 47,
        "line_end": 139,
        "summary": "### Telephony_RadioResult\n\n```c\nenum Telephony_RadioResult\n```\n\n**描述**\n\n错误码类型枚举。\n\n**起始版本：** 13\n\n| 枚"
      }
    ]
  }
}