{
  "doc_id": "js-apis-bundleManager-hapModuleInfo",
  "title": "HapModuleInfo",
  "path": "zh-cn/application-dev/reference/apis-ability-kit/js-apis-bundleManager-hapModuleInfo.md",
  "relative_path": "../../docs/zh-cn/application-dev/reference/apis-ability-kit/js-apis-bundleManager-hapModuleInfo.md",
  "metadata": {
    "kit": "Ability Kit",
    "subsystem": "BundleManager",
    "owner": "@wanghang904",
    "designer": "@hanfeng6",
    "tester": "@kongjing2",
    "adviser": "@Brilliantry_Rui"
  },
  "summary": "Ability Kit BundleManager 模块的 HapModuleInfo，提供相关接口和功能说明。",
  "structure": {
    "title": "HapModuleInfo",
    "sections": [
      {
        "section_id": "section-1",
        "title": "导入模块",
        "level": 2,
        "line_start": 14,
        "line_end": 19,
        "summary": "```ts\nimport { bundleManager } from '@kit.AbilityKit';\n```"
      },
      {
        "section_id": "section-2",
        "title": "HapModuleInfo",
        "level": 2,
        "line_start": 20,
        "line_end": 47,
        "summary": "**系统能力：** SystemCapability.BundleManager.BundleFramework.Core\n\n| 名称                              |"
      },
      {
        "section_id": "section-3",
        "title": "PreloadItem",
        "level": 2,
        "line_start": 48,
        "line_end": 59,
        "summary": "描述原子化服务中模块的预加载模块信息。\n\n**原子化服务API：** 从API version 11开始，该接口支持在原子化服务中使用。\n\n**系统能力：** SystemCapability.Bu"
      },
      {
        "section_id": "section-4",
        "title": "Dependency",
        "level": 2,
        "line_start": 60,
        "line_end": 73,
        "summary": "描述模块所依赖的动态共享库信息。\n\n**原子化服务API：** 从API version 11开始，该接口支持在原子化服务中使用。\n\n**系统能力：** SystemCapability.Bundl"
      },
      {
        "section_id": "section-5",
        "title": "RouterItem<sup>12+</sup>",
        "level": 2,
        "line_start": 74,
        "line_end": 89,
        "summary": "描述模块配置的路由表信息。\n\n**原子化服务API：** 从API version 12开始，该接口支持在原子化服务中使用。\n\n**系统能力：** SystemCapability.BundleMa"
      },
      {
        "section_id": "section-6",
        "title": "DataItem<sup>12+</sup>",
        "level": 2,
        "line_start": 90,
        "line_end": 102,
        "summary": "描述模块配置的路由表中的自定义数据。\n\n**原子化服务API：** 从API version 12开始，该接口支持在原子化服务中使用。\n\n**系统能力：** SystemCapability.Bun"
      }
    ]
  }
}