{
  "doc_id": "js-apis-app-ability-embeddedUIExtensionAbility",
  "title": "@ohos.app.ability.EmbeddedUIExtensionAbility (支持跨进程界面嵌入的ExtensionAbility组件)",
  "path": "zh-cn/application-dev/reference/apis-ability-kit/js-apis-app-ability-embeddedUIExtensionAbility.md",
  "relative_path": "../../docs/zh-cn/application-dev/reference/apis-ability-kit/js-apis-app-ability-embeddedUIExtensionAbility.md",
  "metadata": {
    "kit": "Ability Kit",
    "subsystem": "Ability",
    "owner": "@zexin_c",
    "designer": "@li-weifeng2024",
    "tester": "@lixueqing513",
    "adviser": "@huipeizi"
  },
  "summary": "Ability Kit Ability 模块的 @ohos.app.ability.EmbeddedUIExtensionAbility (支持跨进程界面嵌入的ExtensionAbility组件)，提供相关接口和功能说明。",
  "structure": {
    "title": "@ohos.app.ability.EmbeddedUIExtensionAbility (支持跨进程界面嵌入的ExtensionAbility组件)",
    "sections": [
      {
        "section_id": "section-1",
        "title": "导入模块",
        "level": 2,
        "line_start": 22,
        "line_end": 27,
        "summary": "```ts\nimport { EmbeddedUIExtensionAbility } from '@kit.AbilityKit';\n```"
      },
      {
        "section_id": "section-2",
        "title": "EmbeddedUIExtensionAbility",
        "level": 2,
        "line_start": 28,
        "line_end": 37,
        "summary": "EmbeddedUIExtensionAbility为开发者提供了跨进程界面嵌入的能力，继承自[UIExtensionAbility](js-apis-app-ability-uiExtension"
      }
    ]
  }
}