{
  "doc_id": "js-apis-data-UdmfComponents",
  "title": "@ohos.data.UdmfComponents(内容卡片)",
  "path": "zh-cn/application-dev/reference/apis-arkdata/js-apis-data-UdmfComponents.md",
  "relative_path": "../../docs/zh-cn/application-dev/reference/apis-arkdata/js-apis-data-UdmfComponents.md",
  "metadata": {
    "kit": "ArkData",
    "subsystem": "DistributedDataManager",
    "owner": "@jcwen",
    "designer": "@junathuawei1; @zph000",
    "tester": "@lj_liujing; @yippo; @logic42",
    "adviser": "@ge-yafang"
  },
  "summary": "ArkData DistributedDataManager 模块的 @ohos.data.UdmfComponents(内容卡片)，提供相关接口和功能说明。",
  "structure": {
    "title": "@ohos.data.UdmfComponents(内容卡片)",
    "sections": [
      {
        "section_id": "section-1",
        "title": "导入模块",
        "level": 2,
        "line_start": 15,
        "line_end": 20,
        "summary": "```js\nimport { ContentFormCard, FormType } from '@kit.ArkData';\n```"
      },
      {
        "section_id": "section-2",
        "title": "子组件",
        "level": 2,
        "line_start": 21,
        "line_end": 24,
        "summary": "子组件相关内容"
      },
      {
        "section_id": "section-3",
        "title": "ContentFormCard",
        "level": 2,
        "line_start": 25,
        "line_end": 42,
        "summary": "ContentFormCard({contentFormData: uniformDataStruct.ContentForm, formType: FormType, formWidth?: nu"
      },
      {
        "section_id": "section-4",
        "title": "FormType",
        "level": 2,
        "line_start": 43,
        "line_end": 54,
        "summary": "内容卡片类型枚举，提供了大、中、小三种尺寸。\n\n**系统能力：** SystemCapability.DistributedDataManager.UDMF.Core\n\n| 名称"
      },
      {
        "section_id": "section-5",
        "title": "示例",
        "level": 2,
        "line_start": 55,
        "line_end": 116,
        "summary": "```ts\nimport { uniformDataStruct } from '@kit.ArkData'\n\n@Entry\n@Component\nstruct Index {\n  @State c"
      }
    ]
  }
}